rdsalesorder/EcsInterface.py
rdsalesorder/__init__.py
rdsalesorder/mainModel.py
rdsalesorder/metadata.py
rdsalesorder/operation.py
rdsalesorder/utility.py
tests/__init__.py
tests/test.py
tests/test_demo.py
tests/test_dms_demo.py
tests/test_ecs.py
rdsalesorder-1.4.7.dist-info/METADATA
rdsalesorder-1.4.7.dist-info/WHEEL
rdsalesorder-1.4.7.dist-info/top_level.txt
rdsalesorder-1.4.7.dist-info/RECORD
